django_session_timeout_2025/__init__.py
django_session_timeout_2025/middleware.py
django_session_timeout_2025-0.1.1.dist-info/licenses/LICENSE
django_session_timeout_2025-0.1.1.dist-info/METADATA
django_session_timeout_2025-0.1.1.dist-info/WHEEL
django_session_timeout_2025-0.1.1.dist-info/top_level.txt
django_session_timeout_2025-0.1.1.dist-info/RECORD
